groupdocs_merger_cloud/__init__.py
groupdocs_merger_cloud/api_client.py
groupdocs_merger_cloud/api_exception.py
groupdocs_merger_cloud/auth.py
groupdocs_merger_cloud/configuration.py
groupdocs_merger_cloud/rest.py
groupdocs_merger_cloud/apis/__init__.py
groupdocs_merger_cloud/apis/document_api.py
groupdocs_merger_cloud/apis/file_api.py
groupdocs_merger_cloud/apis/folder_api.py
groupdocs_merger_cloud/apis/info_api.py
groupdocs_merger_cloud/apis/license_api.py
groupdocs_merger_cloud/apis/pages_api.py
groupdocs_merger_cloud/apis/security_api.py
groupdocs_merger_cloud/apis/storage_api.py
groupdocs_merger_cloud/models/__init__.py
groupdocs_merger_cloud/models/api_error.py
groupdocs_merger_cloud/models/api_error_response.py
groupdocs_merger_cloud/models/consumption_result.py
groupdocs_merger_cloud/models/disc_usage.py
groupdocs_merger_cloud/models/document_result.py
groupdocs_merger_cloud/models/error.py
groupdocs_merger_cloud/models/error_details.py
groupdocs_merger_cloud/models/extract_options.py
groupdocs_merger_cloud/models/file_info.py
groupdocs_merger_cloud/models/file_version.py
groupdocs_merger_cloud/models/file_versions.py
groupdocs_merger_cloud/models/files_list.py
groupdocs_merger_cloud/models/files_upload_result.py
groupdocs_merger_cloud/models/format.py
groupdocs_merger_cloud/models/formats_result.py
groupdocs_merger_cloud/models/import_options.py
groupdocs_merger_cloud/models/info_result.py
groupdocs_merger_cloud/models/join_item.py
groupdocs_merger_cloud/models/join_options.py
groupdocs_merger_cloud/models/mix_pages_item.py
groupdocs_merger_cloud/models/mix_pages_options.py
groupdocs_merger_cloud/models/move_options.py
groupdocs_merger_cloud/models/multi_document_result.py
groupdocs_merger_cloud/models/object_exist.py
groupdocs_merger_cloud/models/options.py
groupdocs_merger_cloud/models/orientation_options.py
groupdocs_merger_cloud/models/page_info.py
groupdocs_merger_cloud/models/page_options.py
groupdocs_merger_cloud/models/password_result.py
groupdocs_merger_cloud-25.11.dist-info/licenses/LICENSE
groupdocs_merger_cloud-25.11.dist-info/METADATA
groupdocs_merger_cloud-25.11.dist-info/WHEEL
groupdocs_merger_cloud-25.11.dist-info/top_level.txt
groupdocs_merger_cloud-25.11.dist-info/RECORD
